stabilo/__init__.py
stabilo/stabilo.py
stabilo/utils.py
stabilo/cfg/default.yaml
stabilo/thresholds/models/AKAZE/model_mask_False_clahe_False.txt
stabilo/thresholds/models/AKAZE/model_mask_False_clahe_True.txt
stabilo/thresholds/models/AKAZE/model_mask_True_clahe_False.txt
stabilo/thresholds/models/AKAZE/model_mask_True_clahe_True.txt
stabilo/thresholds/models/BRISK/model_mask_False_clahe_False.txt
stabilo/thresholds/models/BRISK/model_mask_False_clahe_True.txt
stabilo/thresholds/models/BRISK/model_mask_True_clahe_False.txt
stabilo/thresholds/models/BRISK/model_mask_True_clahe_True.txt
stabilo/thresholds/models/KAZE/model_mask_False_clahe_False.txt
stabilo/thresholds/models/KAZE/model_mask_False_clahe_True.txt
stabilo/thresholds/models/KAZE/model_mask_True_clahe_False.txt
stabilo/thresholds/models/KAZE/model_mask_True_clahe_True.txt
stabilo-1.1.0.dist-info/licenses/LICENSE
stabilo-1.1.0.dist-info/METADATA
stabilo-1.1.0.dist-info/WHEEL
stabilo-1.1.0.dist-info/top_level.txt
stabilo-1.1.0.dist-info/RECORD
