Metadata-Version: 2.4
Name: stabilo
Version: 1.1.0
Summary: Stabilizes video or extracted trajectories with respect to a selected reference frame in the video, with optional user-provided masks.
Author-email: Robert Fonod <robert.fonod@ieee.org>
License: MIT License
Project-URL: Homepage, https://github.com/rfonod/stabilo/
Project-URL: Repository, https://github.com/rfonod/stabilo/
Project-URL: Changelog, https://github.com/rfonod/stabilo/releases
Project-URL: Issues, https://github.com/rfonod/stabilo/issues/
Keywords: stabilo,video-stabilization,object-stabilization,mask,reference-frame,computer-vision
Classifier: Development Status :: 5 - Production/Stable
Classifier: License :: OSI Approved :: MIT License
Classifier: Operating System :: OS Independent
Classifier: Programming Language :: Python :: 3
Classifier: Programming Language :: Python :: 3.9
Classifier: Programming Language :: Python :: 3.10
Classifier: Programming Language :: Python :: 3.11
Classifier: Programming Language :: Python :: 3.12
Classifier: Programming Language :: Python :: 3.13
Classifier: Intended Audience :: Developers
Classifier: Intended Audience :: Science/Research
Classifier: Topic :: Scientific/Engineering
Classifier: Topic :: Software Development
Classifier: Topic :: Multimedia :: Video
Requires-Python: >=3.9
License-File: LICENSE
Requires-Dist: numpy<2.0,>=1.26.4
Requires-Dist: opencv-python>=4.6.0
Requires-Dist: pyyaml>=5.3.1
Requires-Dist: tqdm>=4.64.0
Provides-Extra: extras
Requires-Dist: matplotlib>=3.5.0; extra == "extras"
Provides-Extra: dev
Requires-Dist: pytest>=7.0.0; extra == "dev"
Requires-Dist: ruff>=0.11.0; extra == "dev"
Requires-Dist: matplotlib>=3.5.0; extra == "dev"
Dynamic: license-file
